directv/__init__.py
directv/__version__.py
directv/const.py
directv/directv.py
directv/exceptions.py
directv/models.py
directv/utils.py
directv-0.4.0.dist-info/LICENSE
directv-0.4.0.dist-info/METADATA
directv-0.4.0.dist-info/WHEEL
directv-0.4.0.dist-info/top_level.txt
directv-0.4.0.dist-info/RECORD
