Metadata-Version: 2.1
Name: directv
Version: 0.4.0
Summary: Asynchronous Python client for DirecTV (SHEF).
Home-page: https://github.com/ctalkington/python-directv
Author: Chris Talkington
Author-email: chris@talkingtontech.com
License: MIT license
Keywords: directv,api,async,client,shef
Platform: UNKNOWN
Classifier: Development Status :: 4 - Beta
Classifier: Framework :: AsyncIO
Classifier: Intended Audience :: Developers
Classifier: License :: OSI Approved :: MIT License
Classifier: Natural Language :: English
Classifier: Programming Language :: Python :: 3.7
Classifier: Programming Language :: Python :: 3.8
Classifier: Programming Language :: Python :: 3
Classifier: Topic :: Software Development :: Libraries :: Python Modules
